extratools_api/__init__.py
extratools_api/crudl.py
extratools_api/py.typed
extratools_api-0.1.2.dist-info/METADATA
extratools_api-0.1.2.dist-info/WHEEL
extratools_api-0.1.2.dist-info/licenses/LICENSE
extratools_api-0.1.2.dist-info/RECORD
