Metadata-Version: 2.4
Name: extratools-api
Version: 0.1.2
Project-URL: Repository, https://github.com/chuanconggao/extratools-api
Author-email: Chuancong Gao <chuanconggao@users.noreply.github.com>
License-Expression: MIT
License-File: LICENSE
Requires-Python: >=3.12
Requires-Dist: extratools-core>=0.1.29
Provides-Extra: fastapi
Requires-Dist: fastapi>=0.115.12; extra == 'fastapi'
